examples/__init__.py
llmdeploy/__init__.py
llmdeploy/model.py
llmdeploy/version.py
llmdeploy/serve/__init__.py
llmdeploy/serve/client.py
llmdeploy/serve/fastertransformer/__init__.py
llmdeploy/serve/fastertransformer/chatbot.py
llmdeploy/serve/fastertransformer/deploy.py
llmdeploy/serve/fastertransformer/utils.py
llmdeploy/webui/__init__.py
llmdeploy/webui/app.py
llmdeploy/webui/strings.py
llmdeploy/webui/styles.py
llmdeploy-0.0.1.dist-info/LICENSE
llmdeploy-0.0.1.dist-info/METADATA
llmdeploy-0.0.1.dist-info/WHEEL
llmdeploy-0.0.1.dist-info/top_level.txt
llmdeploy-0.0.1.dist-info/RECORD
