Metadata-Version: 2.1
Name: llmdeploy
Version: 0.0.1
Summary: triton inference service of llama
Home-page: UNKNOWN
Author: OpenMMLab
Author-email: openmmlab@gmail.com
License: UNKNOWN
Platform: UNKNOWN
Classifier: Programming Language :: Python :: 3.8
Classifier: Programming Language :: Python :: 3.9
Classifier: Programming Language :: Python :: 3.10
Classifier: Intended Audience :: Developers
Classifier: Intended Audience :: Education
Classifier: Intended Audience :: Science/Research
License-File: LICENSE
